{
	"song": {
		"speed": 3.2,
		"stage": "scenty",
		"player1": "bf",
		"player2": "amelia",
		"player3": null,
		"events": [
			[
				38666.6666666667,
				[
					[
						"Add Camera Zoom",
						"0.015",
						"0.03"
					]
				]
			],
			[
				38833.3333333333,
				[
					[
						"Add Camera Zoom",
						"0.015",
						"0.03"
					]
				]
			],
			[
				39000,
				[
					[
						"Add Camera Zoom",
						"0.020",
						"0.04"
					]
				]
			],
			[
				39166.6666666667,
				[
					[
						"Add Camera Zoom",
						"0.015",
						"0.03"
					]
				]
			],
			[
				39333.3333333333,
				[
					[
						"Add Camera Zoom",
						"0.015",
						"0.03"
					]
				]
			],
			[
				39500,
				[
					[
						"Add Camera Zoom",
						"0.015",
						"0.03"
					]
				]
			],
			[
				39583.3333333333,
				[
					[
						"Add Camera Zoom",
						"0.025",
						"0.05"
					]
				]
			],
			[
				39666.6666666667,
				[
					[
						"Add Camera Zoom",
						"0.015",
						"0.03"
					]
				]
			],
			[
				39833.3333333333,
				[
					[
						"Add Camera Zoom",
						"0.015",
						"0.03"
					]
				]
			],
			[
				40000,
				[
					[
						"Add Camera Zoom",
						"0.015",
						"0.03"
					]
				]
			],
			[
				40166.6666666667,
				[
					[
						"Add Camera Zoom",
						"0.015",
						"0.03"
					]
				]
			],
			[
				40333.3333333333,
				[
					[
						"Add Camera Zoom",
						"0.020",
						"0.04"
					]
				]
			],
			[
				40500,
				[
					[
						"Add Camera Zoom",
						"0.015",
						"0.03"
					]
				]
			],
			[
				40666.6666666667,
				[
					[
						"Add Camera Zoom",
						"0.015",
						"0.03"
					]
				]
			],
			[
				40833.3333333333,
				[
					[
						"Add Camera Zoom",
						"0.015",
						"0.03"
					]
				]
			],
			[
				40916.6666666667,
				[
					[
						"Add Camera Zoom",
						"0.025",
						"0.05"
					]
				]
			],
			[
				41000,
				[
					[
						"Add Camera Zoom",
						"0.015",
						"0.03"
					]
				]
			],
			[
				41166.6666666667,
				[
					[
						"Add Camera Zoom",
						"0.015",
						"0.03"
					]
				]
			],
			[
				41333.3333333333,
				[
					[
						"Add Camera Zoom",
						"0.015",
						"0.03"
					]
				]
			],
			[
				41500,
				[
					[
						"Add Camera Zoom",
						"0.015",
						"0.03"
					]
				]
			],
			[
				41666.6666666667,
				[
					[
						"Add Camera Zoom",
						"0.020",
						"0.04"
					]
				]
			],
			[
				41833.3333333333,
				[
					[
						"Add Camera Zoom",
						"0.015",
						"0.03"
					]
				]
			],
			[
				42000,
				[
					[
						"Add Camera Zoom",
						"0.015",
						"0.03"
					]
				]
			],
			[
				42166.6666666667,
				[
					[
						"Add Camera Zoom",
						"0.015",
						"0.03"
					]
				]
			],
			[
				42250,
				[
					[
						"Add Camera Zoom",
						"0.025",
						"0.05"
					]
				]
			],
			[
				42333.3333333333,
				[
					[
						"Add Camera Zoom",
						"0.015",
						"0.03"
					]
				]
			],
			[
				42500,
				[
					[
						"Add Camera Zoom",
						"0.015",
						"0.03"
					]
				]
			],
			[
				42666.6666666667,
				[
					[
						"Add Camera Zoom",
						"0.015",
						"0.03"
					]
				]
			],
			[
				42833.3333333333,
				[
					[
						"Add Camera Zoom",
						"0.015",
						"0.03"
					]
				]
			],
			[
				42916.6666666667,
				[
					[
						"Add Camera Zoom",
						"0.015",
						"0.03"
					]
				]
			],
			[
				43000,
				[
					[
						"Add Camera Zoom",
						"0.027",
						"0.05"
					]
				]
			],
			[
				43166.6666666667,
				[
					[
						"Add Camera Zoom",
						"0.015",
						"0.03"
					]
				]
			],
			[
				43250,
				[
					[
						"Add Camera Zoom",
						"0.027",
						"0.05"
					]
				]
			],
			[
				43333.3333333333,
				[
					[
						"Add Camera Zoom",
						"0.027",
						"0.05"
					]
				]
			],
			[
				43500,
				[
					[
						"Add Camera Zoom",
						"0.015",
						"0.03"
					]
				]
			],
			[
				43583.3333333333,
				[
					[
						"Add Camera Zoom",
						"0.027",
						"0.05"
					]
				]
			],
			[
				43666.6666666667,
				[
					[
						"Add Camera Zoom",
						"0.027",
						"0.05"
					]
				]
			],
			[
				43833.3333333333,
				[
					[
						"Add Camera Zoom",
						"0.015",
						"0.03"
					]
				]
			],
			[
				44000,
				[
					[
						"Add Camera Zoom",
						"0.040",
						"0.08"
					]
				]
			],
			[
				49333.3333333334,
				[
					[
						"Add Camera Zoom",
						"0.010",
						"0.02"
					]
				]
			],
			[
				50166.6666666667,
				[
					[
						"Add Camera Zoom",
						"0.010",
						"0.02"
					]
				]
			],
			[
				50666.6666666667,
				[
					[
						"Add Camera Zoom",
						"0.010",
						"0.02"
					]
				]
			],
			[
				51500,
				[
					[
						"Add Camera Zoom",
						"0.010",
						"0.02"
					]
				]
			],
			[
				52000,
				[
					[
						"Add Camera Zoom",
						"0.010",
						"0.02"
					]
				]
			],
			[
				52833.3333333334,
				[
					[
						"Add Camera Zoom",
						"0.010",
						"0.02"
					]
				]
			],
			[
				53333.3333333334,
				[
					[
						"Add Camera Zoom",
						"0.010",
						"0.02"
					]
				]
			],
			[
				54166.6666666667,
				[
					[
						"Add Camera Zoom",
						"0.010",
						"0.02"
					]
				]
			],
			[
				54666.6666666667,
				[
					[
						"Add Camera Zoom",
						"0.030",
						"0.04"
					]
				]
			],
			[
				65333.3333333334,
				[
					[
						"Add Camera Zoom",
						"0.050",
						"0.02"
					]
				]
			],
			[
				76666.6666666667,
				[
					[
						"Add Camera Zoom",
						"0.015",
						"0.03"
					]
				]
			],
			[
				77000,
				[
					[
						"Add Camera Zoom",
						"0.015",
						"0.03"
					]
				]
			],
			[
				77333.3333333333,
				[
					[
						"Add Camera Zoom",
						"0.015",
						"0.03"
					]
				]
			],
			[
				77500,
				[
					[
						"Add Camera Zoom",
						"0.015",
						"0.03"
					]
				]
			],
			[
				77583.3333333333,
				[
					[
						"Add Camera Zoom",
						"0.015",
						"0.03"
					]
				]
			],
			[
				77666.6666666667,
				[
					[
						"Add Camera Zoom",
						"0.015",
						"0.03"
					]
				]
			],
			[
				78000,
				[
					[
						"Add Camera Zoom",
						"0.015",
						"0.03"
					]
				]
			],
			[
				78166.6666666667,
				[
					[
						"Add Camera Zoom",
						"0.015",
						"0.03"
					]
				]
			],
			[
				78250,
				[
					[
						"Add Camera Zoom",
						"0.015",
						"0.03"
					]
				]
			],
			[
				78333.3333333333,
				[
					[
						"Add Camera Zoom",
						"0.015",
						"0.03"
					]
				]
			],
			[
				94666.6666666667,
				[
					[
						"Add Camera Zoom",
						"0.015",
						"0.03"
					]
				]
			],
			[
				94666.6666666667,
				[
					[
						"Add Camera Zoom",
						"0.015",
						"0.03"
					]
				]
			],
			[
				94833.3333333333,
				[
					[
						"Add Camera Zoom",
						"0.015",
						"0.03"
					]
				]
			],
			[
				94833.3333333333,
				[
					[
						"Add Camera Zoom",
						"0.015",
						"0.03"
					]
				]
			],
			[
				95000,
				[
					[
						"Add Camera Zoom",
						"0.020",
						"0.04"
					]
				]
			],
			[
				95000,
				[
					[
						"Add Camera Zoom",
						"0.020",
						"0.04"
					]
				]
			],
			[
				95166.6666666667,
				[
					[
						"Add Camera Zoom",
						"0.015",
						"0.03"
					]
				]
			],
			[
				95166.6666666667,
				[
					[
						"Add Camera Zoom",
						"0.015",
						"0.03"
					]
				]
			],
			[
				95333.3333333333,
				[
					[
						"Add Camera Zoom",
						"0.015",
						"0.03"
					]
				]
			],
			[
				95333.3333333333,
				[
					[
						"Add Camera Zoom",
						"0.015",
						"0.03"
					]
				]
			],
			[
				95500,
				[
					[
						"Add Camera Zoom",
						"0.015",
						"0.03"
					]
				]
			],
			[
				95500,
				[
					[
						"Add Camera Zoom",
						"0.015",
						"0.03"
					]
				]
			],
			[
				95583.3333333333,
				[
					[
						"Add Camera Zoom",
						"0.025",
						"0.05"
					]
				]
			],
			[
				95583.3333333333,
				[
					[
						"Add Camera Zoom",
						"0.025",
						"0.05"
					]
				]
			],
			[
				95666.6666666667,
				[
					[
						"Add Camera Zoom",
						"0.015",
						"0.03"
					]
				]
			],
			[
				95666.6666666667,
				[
					[
						"Add Camera Zoom",
						"0.015",
						"0.03"
					]
				]
			],
			[
				95833.3333333333,
				[
					[
						"Add Camera Zoom",
						"0.015",
						"0.03"
					]
				]
			],
			[
				95833.3333333333,
				[
					[
						"Add Camera Zoom",
						"0.015",
						"0.03"
					]
				]
			],
			[
				96000,
				[
					[
						"Add Camera Zoom",
						"0.015",
						"0.03"
					]
				]
			],
			[
				96166.6666666667,
				[
					[
						"Add Camera Zoom",
						"0.015",
						"0.03"
					]
				]
			],
			[
				96333.3333333333,
				[
					[
						"Add Camera Zoom",
						"0.020",
						"0.04"
					]
				]
			],
			[
				96500,
				[
					[
						"Add Camera Zoom",
						"0.015",
						"0.03"
					]
				]
			],
			[
				96666.6666666667,
				[
					[
						"Add Camera Zoom",
						"0.015",
						"0.03"
					]
				]
			],
			[
				96833.3333333333,
				[
					[
						"Add Camera Zoom",
						"0.015",
						"0.03"
					]
				]
			],
			[
				96916.6666666667,
				[
					[
						"Add Camera Zoom",
						"0.025",
						"0.05"
					]
				]
			],
			[
				97000,
				[
					[
						"Add Camera Zoom",
						"0.015",
						"0.03"
					]
				]
			],
			[
				97166.6666666667,
				[
					[
						"Add Camera Zoom",
						"0.015",
						"0.03"
					]
				]
			],
			[
				97333.3333333333,
				[
					[
						"Add Camera Zoom",
						"0.015",
						"0.03"
					]
				]
			],
			[
				97500,
				[
					[
						"Add Camera Zoom",
						"0.015",
						"0.03"
					]
				]
			],
			[
				97666.6666666667,
				[
					[
						"Add Camera Zoom",
						"0.020",
						"0.04"
					]
				]
			],
			[
				97833.3333333333,
				[
					[
						"Add Camera Zoom",
						"0.015",
						"0.03"
					]
				]
			],
			[
				98000,
				[
					[
						"Add Camera Zoom",
						"0.015",
						"0.03"
					]
				]
			],
			[
				98166.6666666667,
				[
					[
						"Add Camera Zoom",
						"0.015",
						"0.03"
					]
				]
			],
			[
				98250,
				[
					[
						"Add Camera Zoom",
						"0.025",
						"0.05"
					]
				]
			],
			[
				98333.3333333333,
				[
					[
						"Add Camera Zoom",
						"0.015",
						"0.03"
					]
				]
			],
			[
				98500,
				[
					[
						"Add Camera Zoom",
						"0.015",
						"0.03"
					]
				]
			],
			[
				98666.6666666667,
				[
					[
						"Add Camera Zoom",
						"0.015",
						"0.03"
					]
				]
			],
			[
				98833.3333333333,
				[
					[
						"Add Camera Zoom",
						"0.015",
						"0.03"
					]
				]
			],
			[
				99000,
				[
					[
						"Add Camera Zoom",
						"0.020",
						"0.04"
					]
				]
			],
			[
				99166.6666666667,
				[
					[
						"Add Camera Zoom",
						"0.015",
						"0.03"
					]
				]
			],
			[
				99249.9999999999,
				[
					[
						"Add Camera Zoom",
						"0.020",
						"0.04"
					]
				]
			],
			[
				99333.3333333333,
				[
					[
						"Add Camera Zoom",
						"0.015",
						"0.03"
					]
				]
			],
			[
				99500,
				[
					[
						"Add Camera Zoom",
						"0.015",
						"0.03"
					]
				]
			],
			[
				99583.3333333333,
				[
					[
						"Add Camera Zoom",
						"0.025",
						"0.05"
					]
				]
			],
			[
				99666.6666666667,
				[
					[
						"Add Camera Zoom",
						"0.015",
						"0.03"
					]
				]
			],
			[
				99833.3333333333,
				[
					[
						"Add Camera Zoom",
						"0.015",
						"0.03"
					]
				]
			]
		],
		"notes": [],
		"splashSkin": null,
		"validScore": false,
		"gfVersion": "gfbutomgsheisnthere",
		"bpm": 180,
		"arrowSkin": null,
		"needsVoices": false,
		"song": "scenty"
	}
}